kq_lmpc_quadrotor/QuadrotorKoopman.py
kq_lmpc_quadrotor/__init__.py
kq_lmpc_quadrotor/kqlmpc_demo.py
kq_lmpc_quadrotor/lqr_demo.py
kq_lmpc_quadrotor/Utils/Dynamics.py
kq_lmpc_quadrotor/Utils/Reference_Generator_DFB.py
kq_lmpc_quadrotor/Utils/__init__.py
kq_lmpc_quadrotor/Utils/lqr_utils.py
kq_lmpc_quadrotor/Utils/quadrotor_util.py
kq_lmpc_quadrotor/Viz/Animation.py
kq_lmpc_quadrotor/Viz/Plotting.py
kq_lmpc_quadrotor/Viz/__init__.py
kq_lmpc_quadrotor/mpc/__init__.py
kq_lmpc_quadrotor/mpc/kq_lmpc.py
kq_lmpc_quadrotor/mpc/mpc_utils.py
kq_lmpc_quadrotor/mpc/nmpc.py
kq_lmpc_quadrotor-1.1.2.dist-info/licenses/LICENSE
kq_lmpc_quadrotor-1.1.2.dist-info/METADATA
kq_lmpc_quadrotor-1.1.2.dist-info/WHEEL
kq_lmpc_quadrotor-1.1.2.dist-info/top_level.txt
kq_lmpc_quadrotor-1.1.2.dist-info/RECORD
