Metadata-Version: 2.4
Name: kq-lmpc-quadrotor
Version: 1.1.2
Summary: A complete, hardware-ready Python package for Koopman-based Linear Model Predictive Control (LMPC), delivering real-time trajectory tracking for quadrotors using analytical Koopman lifting (no training data required).
Home-page: https://santoshrajkumar.github.io
Author: Santosh Rajkumar
Author-email: Santosh Rajkumar <rajkumar.36@osu.edu>
License: MIT License
Project-URL: Homepage, https://github.com/santoshrajkumar/kq-lmpc-quadrotor
Requires-Python: >=3.8
License-File: LICENSE
Requires-Dist: numpy>=1.20
Requires-Dist: scipy>=1.8
Requires-Dist: casadi>=3.6.3
Requires-Dist: matplotlib>=3.5
Requires-Dist: pyquaternion>=0.9.9
Dynamic: license-file
